cocoremover/.ipynb_checkpoints/__init__-checkpoint.py
cocoremover/.ipynb_checkpoints/cocoremover-checkpoint.py
cocoremover/.ipynb_checkpoints/logutils-checkpoint.py
cocoremover/.ipynb_checkpoints/unipruner-checkpoint.py
cocoremover/__init__.py
cocoremover/cocoremover.py
cocoremover/logutils.py
cocoremover-0.1.2.dist-info/LICENSE.txt
cocoremover-0.1.2.dist-info/METADATA
cocoremover-0.1.2.dist-info/WHEEL
cocoremover-0.1.2.dist-info/entry_points.txt
cocoremover-0.1.2.dist-info/RECORD
