Metadata-Version: 2.3
Name: cocoremover
Version: 0.1.2
Summary: 
License: GNU General Public License v3.0
Author: Gioele Lazzari
Requires-Python: >=3.9
Classifier: License :: Other/Proprietary License
Classifier: Programming Language :: Python :: 3
Classifier: Programming Language :: Python :: 3.9
Classifier: Programming Language :: Python :: 3.10
Classifier: Programming Language :: Python :: 3.11
Classifier: Programming Language :: Python :: 3.12
Classifier: Programming Language :: Python :: 3.13
Requires-Dist: biopython (>=1.80)
Requires-Dist: colorlog (>=6.9.0)
Requires-Dist: openpyxl (>=3.1.0)
Requires-Dist: pandas (>=2.0.0)
